{
  "db_name": "PostgreSQL",
  "query": "INSERT INTO user_credits (user_id, balance_usd, updated_at)\n           VALUES ($1, $2, NOW())\n           ON CONFLICT (user_id) DO UPDATE SET\n               balance_usd = user_credits.balance_usd + $2,\n               updated_at = NOW()\n           RETURNING balance_usd",
  "describe": {
    "columns": [
      {
        "ordinal": 0,
        "name": "balance_usd",
        "type_info": "Float8"
      }
    ],
    "parameters": {
      "Left": [
        "Text",
        "Float8"
      ]
    },
    "nullable": [
      false
    ]
  },
  "hash": "5737ee677982e44e3c13f2d715647734d5066c46a6a3f1e6ccf405738cee6afb"
}
